jargon_distance/JargonDistance.py
jargon_distance/__init__.py
jargon_distance/analysis/JargonDistanceAnalysis.py
jargon_distance/analysis/__init__.py
jargon_distance-0.1.5.dist-info/LICENSE
jargon_distance-0.1.5.dist-info/METADATA
jargon_distance-0.1.5.dist-info/WHEEL
jargon_distance-0.1.5.dist-info/top_level.txt
jargon_distance-0.1.5.dist-info/RECORD
