Metadata-Version: 2.1
Name: jargon-distance
Version: 0.1.5
Summary: Calculate jargon distance metric between texts
Home-page: https://github.com/h1-the-swan/jargon_distance
Author: Jason Portenoy
Author-email: jason.portenoy@gmail.com
License: Copyright 2018 Jason Portenoy
Requires-Dist: numpy
Requires-Dist: six
